{
  "hash": "a7a598b2",
  "configHash": "12def5cd",
  "lockfileHash": "3c610430",
  "browserHash": "a58fa64f",
  "optimized": {
    "react-dom/client": {
      "src": "../../node_modules/react-dom/client.js",
      "file": "react-dom_client.js",
      "fileHash": "b1b57499",
      "needsInterop": true
    },
    "react": {
      "src": "../../node_modules/react/index.js",
      "file": "react.js",
      "fileHash": "58324120",
      "needsInterop": true
    },
    "react/jsx-dev-runtime": {
      "src": "../../node_modules/react/jsx-dev-runtime.js",
      "file": "react_jsx-dev-runtime.js",
      "fileHash": "c1746db4",
      "needsInterop": true
    }
  },
  "chunks": {
    "react-DGPCLjpP": {
      "file": "react-DGPCLjpP.js",
      "isDynamicEntry": false
    }
  }
}